pydepinj/__init__.py
pydepinj/dependency_injection.py
pydepinj-0.4.1.dist-info/METADATA
pydepinj-0.4.1.dist-info/WHEEL
pydepinj-0.4.1.dist-info/top_level.txt
pydepinj-0.4.1.dist-info/RECORD
